monero_scripts/__init__.py
monero_scripts/_version.py
monero_scripts/connect_to_node.py
monero_scripts/get_monero_hard_fork_info.py
monero_scripts/get_monero_seed_nodes.py
monero_scripts-0.1.4.dist-info/LICENSE
monero_scripts-0.1.4.dist-info/METADATA
monero_scripts-0.1.4.dist-info/WHEEL
monero_scripts-0.1.4.dist-info/top_level.txt
monero_scripts-0.1.4.dist-info/RECORD
