Metadata-Version: 2.1
Name: monero-scripts
Version: 0.1.4
Summary: Get Monero meta data from Monero source code files.
Home-page: https://github.com/monero-ecosystem/monero_scripts
Author: Norman Moeschter-Schenck
Author-email: <norman.moeschter@gmail.com>
Maintainer: Norman Moeschter-Schenck
Maintainer-email: <norman.moeschter@gmail.com>
License: UNKNOWN
Download-URL: https://github.com/monero-ecosystem/monero_scripts/archive/v0.1.4.tar.gz
Platform: UNKNOWN
Classifier: License :: OSI Approved :: MIT License
Classifier: Operating System :: OS Independent
Classifier: Programming Language :: Python :: 3.4
Classifier: Programming Language :: Python :: 3.5
Classifier: Programming Language :: Python :: 3.6
Classifier: Programming Language :: Python :: 3.7
Requires-Dist: requests (>=2.23.0)
